azure/mgmt/logz/__init__.py
azure/mgmt/logz/_configuration.py
azure/mgmt/logz/_microsoft_logz.py
azure/mgmt/logz/_version.py
azure/mgmt/logz/aio/__init__.py
azure/mgmt/logz/aio/_configuration.py
azure/mgmt/logz/aio/_microsoft_logz.py
azure/mgmt/logz/aio/operations/__init__.py
azure/mgmt/logz/aio/operations/_monitor_operations.py
azure/mgmt/logz/aio/operations/_monitors_operations.py
azure/mgmt/logz/aio/operations/_operations.py
azure/mgmt/logz/aio/operations/_single_sign_on_operations.py
azure/mgmt/logz/aio/operations/_sub_account_operations.py
azure/mgmt/logz/aio/operations/_sub_account_tag_rules_operations.py
azure/mgmt/logz/aio/operations/_tag_rules_operations.py
azure/mgmt/logz/models/__init__.py
azure/mgmt/logz/models/_microsoft_logz_enums.py
azure/mgmt/logz/models/_models.py
azure/mgmt/logz/models/_models_py3.py
azure/mgmt/logz/operations/__init__.py
azure/mgmt/logz/operations/_monitor_operations.py
azure/mgmt/logz/operations/_monitors_operations.py
azure/mgmt/logz/operations/_operations.py
azure/mgmt/logz/operations/_single_sign_on_operations.py
azure/mgmt/logz/operations/_sub_account_operations.py
azure/mgmt/logz/operations/_sub_account_tag_rules_operations.py
azure/mgmt/logz/operations/_tag_rules_operations.py
azure_mgmt_logz-1.0.0.dist-info/METADATA
azure_mgmt_logz-1.0.0.dist-info/WHEEL
azure_mgmt_logz-1.0.0.dist-info/top_level.txt
azure_mgmt_logz-1.0.0.dist-info/RECORD
